{"students":[{"id":2,"name":"张3","gender":0,"age":18,"hobbies":"吃饭,睡觉,打豆豆,LOL"},{"id":3,"name":"张3","gender":0,"age":18,"hobbies":"吃饭,睡觉,打豆豆,LOL"},{"id":4,"name":"张3","gender":0,"age":18,"hobbies":"吃饭,睡觉,打豆豆,LOL"},{"name":"君莫笑","gender":0,"age":"18","hobbies":"吃饭,睡觉,打豆豆,LOL","id":5},{"name":"啊手动阀","gender":1,"age":"12","hobbies":"吃饭","id":6},{"name":"说的发","gender":1,"age":"12","hobbies":"吃饭","id":7},{"name":"11","gender":1,"age":"12","hobbies":"吃饭","id":8},{"name":"君莫笑","gender":0,"age":"13","hobbies":"吃饭,睡觉,打豆豆,LOL","id":9}]}